flagdata/__init__.py
flagdata/analysis/text_analyzer.py
flagdata/analysis/utils/ana_result.py
flagdata/annotation/dist/favicon.ico
flagdata/annotation/dist/index.html
flagdata/annotation/dist/logo.png
flagdata/annotation/dist/css/app.a8158bb5.css
flagdata/annotation/dist/css/chunk-vendors.9d50c827.css
flagdata/annotation/dist/css/user.03de3796.css
flagdata/annotation/dist/js/app.28f0a0ad.js
flagdata/annotation/dist/js/chunk-vendors.40af414c.js
flagdata/annotation/dist/js/fail.c92e81e0.js
flagdata/annotation/dist/js/user.527f6f1e.js
flagdata/cleaner/text_cleaner.py
flagdata/cleaner/resource/emojis.json
flagdata/cleaner/utils/__init__.py
flagdata/cleaner/utils/extractor.py
flagdata/cleaner/utils/filter.py
flagdata/cleaner/utils/initializer.py
flagdata/cleaner/utils/loggings.py
flagdata/cleaner/utils/ruleset.py
flagdata/cleaner/utils/time_formatter.py
flagdata/condensation/data_distillation.py
flagdata/condensation/utils/common_utils.py
flagdata/condensation/utils/data.py
flagdata/condensation/utils/datadistill.py
flagdata/condensation/utils/evaluate.py
flagdata/condensation/utils/model.py
flagdata-1.0.0.dist-info/METADATA
flagdata-1.0.0.dist-info/WHEEL
flagdata-1.0.0.dist-info/licenses/LICENSE
flagdata-1.0.0.dist-info/RECORD
