Metadata-Version: 2.1
Name: flagdata
Version: 1.0.0
Summary: An out-of-the-box toolkit for data processing.
Project-URL: Homepage, https://github.com/cofe-ai/flagdata
Project-URL: Bug Tracker, https://github.com/cofe-ai/flagdata/issues
Author-email: Xuezhi Fang <xzfang@baai.ac.cn>, Zhao Xue <xuezhao@baai.ac.cn>, Hanyu Zhao <hyzhao@baai.ac.cn>, Quanyue Ma <maqy@baai.ac.cn>, Jiahong Leng <jhleng@baai.ac.cn>, Zheng Zhang <zhangz.goal@gmail.com>, Yequan Wang <yqwang@baai.ac.cn>
License-File: LICENSE
Classifier: License :: OSI Approved :: Apache Software License
Classifier: Operating System :: OS Independent
Classifier: Programming Language :: Python :: 3
Requires-Python: >=3.8
Provides-Extra: all
Requires-Dist: loguru>=0.6.0; extra == 'all'
Requires-Dist: lxml>=4.9.1; extra == 'all'
Requires-Dist: nltk>=3.7; extra == 'all'
Requires-Dist: numpy>=1.21.5; extra == 'all'
Requires-Dist: opencc-python-reimplemented>=0.1.6; platform_system == 'Darwin' and extra == 'all'
Requires-Dist: opencc>=1.1.6; platform_system == 'Linux' and extra == 'all'
Requires-Dist: pandas>=1.3.5; extra == 'all'
Requires-Dist: pyyaml>=6.0; extra == 'all'
Requires-Dist: requests>=2.28.1; extra == 'all'
Requires-Dist: tqdm>=4.63.0; extra == 'all'
Requires-Dist: transformers>=4.20.1; extra == 'all'
Requires-Dist: urlextract>=1.6.0; extra == 'all'
Provides-Extra: analysis
Requires-Dist: nltk>=3.7; extra == 'analysis'
Requires-Dist: requests>=2.28.1; extra == 'analysis'
Provides-Extra: cleaner
Requires-Dist: lxml>=4.9.1; extra == 'cleaner'
Requires-Dist: opencc-python-reimplemented>=0.1.6; platform_system == 'Darwin' and extra == 'cleaner'
Requires-Dist: opencc>=1.1.6; platform_system == 'Linux' and extra == 'cleaner'
Requires-Dist: pyyaml>=6.0; extra == 'cleaner'
Requires-Dist: requests>=2.28.1; extra == 'cleaner'
Requires-Dist: tqdm>=4.63.0; extra == 'cleaner'
Requires-Dist: urlextract>=1.6.0; extra == 'cleaner'
Provides-Extra: condensation
Requires-Dist: loguru>=0.6.0; extra == 'condensation'
Requires-Dist: numpy>=1.21.5; extra == 'condensation'
Requires-Dist: pandas>=1.3.5; extra == 'condensation'
Requires-Dist: pyyaml>=6.0; extra == 'condensation'
Requires-Dist: tqdm>=4.63.0; extra == 'condensation'
Requires-Dist: transformers>=4.20.1; extra == 'condensation'
